Metadata-Version: 1.0
Name: cae2scian
Version: 0.3.1
Summary: Industry codes standard translator (CAE and SCIAN)
Home-page: UNKNOWN
Author: UNKNOWN
Author-email: UNKNOWN
License: UNKNOWN
Platform: UNKNOWN
